schmidt_trigger_design.sv
// Code your design here
// Digital Schmidt Trigger 
module schmidt_trigger(in_val,maxi,mini,out_val);
  input [7:0] in_val;
  input [7:0] maxi;
  input [7:0] mini ; 
  output logic out_val;
  wire comp_low , comp_high ;
  assign comp_low = (in_val > mini);
  assign comp_high = (in_val > maxi);
  
  always @(negedge comp_low) begin
    out_val = 1'b1 ;
  end
  
  always @(posedge comp_high) begin
    out_val = 1'b0 ;
  end
  
endmodule

schmidt_trigger_testbench.sv
// Code your testbench here
// or browse Examples

integer i ;

module test ;
  reg [7:0] in_val;
  reg [7:0] maxi;
  reg [7:0] mini ; 
  wire out_val;
  
  schmidt_trigger st(in_val,maxi,mini,out_val);
  
  initial begin 
    // Dump waves
    $dumpfile("dump.vcd");
    $dumpvars(1);
    mini <= 8'b00000110;
    maxi <= 8'b00001100;
    in_val <= 8'd0;
    #5;
    for(int i=0; i<30; i++) begin
      in_val++;
      #1;
    end
    for(int i=0; i<30; i++) begin
      in_val--;
      #1;
    end
  end
  
endmodule

schmidt_trigger_dump.vcd
$date
Sun Jun 25 10:26:36 2023
$end
$version
Riviera-PRO Version 2022.04.117.8517
$end
$timescale
1 ns
$end

$scope module test $end
$var wire 1 ! out_val $end
$var reg 8 " in_val [7:0] $end
$var reg 8 # maxi [7:0] $end
$var reg 8 $ mini [7:0] $end
$upscope $end

$enddefinitions $end
$dumpvars
1!
b0 "
b1100 #
b110 $
$end
#5
b1 "
#6
b10 "
#7
b11 "
#8
b100 "
#9
b101 "
#10
b110 "
#11
b111 "
#12
b1000 "
#13
b1001 "
#14
b1010 "
#15
b1011 "
#16
b1100 "
#17
b1101 "
0!
#18
b1110 "
#19
b1111 "
#20
b10000 "
#21
b10001 "
#22
b10010 "
#23
b10011 "
#24
b10100 "
#25
b10101 "
#26
b10110 "
#27
b10111 "
#28
b11000 "
#29
b11001 "
#30
b11010 "
#31
b11011 "
#32
b11100 "
#33
b11101 "
#34
b11110 "
#35
b11101 "
#36
b11100 "
#37
b11011 "
#38
b11010 "
#39
b11001 "
#40
b11000 "
#41
b10111 "
#42
b10110 "
#43
b10101 "
#44
b10100 "
#45
b10011 "
#46
b10010 "
#47
b10001 "
#48
b10000 "
#49
b1111 "
#50
b1110 "
#51
b1101 "
#52
b1100 "
#53
b1011 "
#54
b1010 "
#55
b1001 "
#56
b1000 "
#57
b111 "
#58
b110 "
1!
#59
b101 "
#60
b100 "
#61
b11 "
#62
b10 "
#63
b1 "
#64
b0 "
